monora/__init__.py
monora/__version__.py
monora/_execution.py
monora/_postinstall.py
monora/ai_act_report.py
monora/alerts.py
monora/api.py
monora/attestation.py
monora/autodetect.py
monora/circuit_breaker.py
monora/config.py
monora/config_migrations.py
monora/config_schema.py
monora/context.py
monora/core.py
monora/data_handling.py
monora/decorators.py
monora/events.py
monora/executive_summary.py
monora/hasher.py
monora/instrumentation.py
monora/lineage.py
monora/logger.py
monora/pdf_report.py
monora/policy.py
monora/propagation.py
monora/registry.py
monora/registry_data.json
monora/reporting.py
monora/runtime.py
monora/schema_validation.py
monora/signing.py
monora/streaming.py
monora/telemetry.py
monora/tracing.py
monora/trust_package.py
monora/verify.py
monora/wal.py
monora/_internal/__init__.py
monora/_internal/enrichers.py
monora/_internal/ids.py
monora/cli/__init__.py
monora/cli/diagnostics.py
monora/cli/init.py
monora/cli/report.py
monora/cli/security_report.py
monora/integrations/__init__.py
monora/integrations/anthropic_sdk.py
monora/integrations/langchain.py
monora/integrations/openai_sdk.py
monora/middleware/__init__.py
monora/middleware/django.py
monora/middleware/fastapi.py
monora/middleware/flask.py
monora/schemas/__init__.py
monora/schemas/config.schema.json
monora/schemas/event.schema.json
monora/schemas/trust_summary.schema.json
monora/sinks/__init__.py
monora/sinks/base.py
monora/sinks/file.py
monora/sinks/https.py
monora/sinks/stdout.py
monora-1.9.3.dist-info/licenses/LICENSE
monora-1.9.3.dist-info/METADATA
monora-1.9.3.dist-info/WHEEL
monora-1.9.3.dist-info/entry_points.txt
monora-1.9.3.dist-info/top_level.txt
monora-1.9.3.dist-info/RECORD
